st_phot/__init__.py
st_phot/cal.py
st_phot/photometry.py
st_phot/util.py
st_phot/wfc3_photometry/photometry_tools/__init__.py
st_phot/wfc3_photometry/photometry_tools/background_median.py
st_phot/wfc3_photometry/photometry_tools/phot_wrapper.py
st_phot/wfc3_photometry/photometry_tools/photometry_with_errors.py
st_phot/wfc3_photometry/photometry_tools/rad_prof.py
st_phot/wfc3_photometry/photometry_tools/__pycache__/__init__.cpython-310.pyc
st_phot/wfc3_photometry/photometry_tools/__pycache__/__init__.cpython-37.pyc
st_phot/wfc3_photometry/photometry_tools/__pycache__/__init__.cpython-38.pyc
st_phot/wfc3_photometry/photometry_tools/__pycache__/background_median.cpython-310.pyc
st_phot/wfc3_photometry/photometry_tools/__pycache__/background_median.cpython-37.pyc
st_phot/wfc3_photometry/photometry_tools/__pycache__/background_median.cpython-38.pyc
st_phot/wfc3_photometry/photometry_tools/__pycache__/phot_wrapper.cpython-310.pyc
st_phot/wfc3_photometry/photometry_tools/__pycache__/phot_wrapper.cpython-37.pyc
st_phot/wfc3_photometry/photometry_tools/__pycache__/phot_wrapper.cpython-38.pyc
st_phot/wfc3_photometry/photometry_tools/__pycache__/photometry_with_errors.cpython-310.pyc
st_phot/wfc3_photometry/photometry_tools/__pycache__/photometry_with_errors.cpython-37.pyc
st_phot/wfc3_photometry/photometry_tools/__pycache__/photometry_with_errors.cpython-38.pyc
st_phot/wfc3_photometry/photometry_tools/__pycache__/rad_prof.cpython-310.pyc
st_phot/wfc3_photometry/photometry_tools/__pycache__/rad_prof.cpython-37.pyc
st_phot/wfc3_photometry/photometry_tools/__pycache__/rad_prof.cpython-38.pyc
st_phot/wfc3_photometry/psf_tools/.DS_Store
st_phot/wfc3_photometry/psf_tools/BundleUtils.py
st_phot/wfc3_photometry/psf_tools/CatalogUtils.py
st_phot/wfc3_photometry/psf_tools/MatchUtils.py
st_phot/wfc3_photometry/psf_tools/PSFPhot.py
st_phot/wfc3_photometry/psf_tools/PSFUtils.py
st_phot/wfc3_photometry/psf_tools/PyFitting.py
st_phot/wfc3_photometry/psf_tools/__init__.py
st_phot-0.1.5.dist-info/METADATA
st_phot-0.1.5.dist-info/WHEEL
st_phot-0.1.5.dist-info/top_level.txt
st_phot-0.1.5.dist-info/RECORD
